[{"draw_number":1246,"draw_date":"2011-10-16","balls":[6,4,4,6]},{"draw_number":1245,"draw_date":"2011-10-15","balls":[4,2,7,1]},{"draw_number":1244,"draw_date":"2011-10-14","balls":[6,9,5,4]},{"draw_number":1243,"draw_date":"2011-10-13","balls":[9,2,3,5]},{"draw_number":1242,"draw_date":"2011-10-12","balls":[1,8,1,7]},{"draw_number":1241,"draw_date":"2011-10-11","balls":[3,2,0,6]},{"draw_number":1240,"draw_date":"2011-10-10","balls":[4,8,2,6]},{"draw_number":1239,"draw_date":"2011-10-09","balls":[0,7,6,9]},{"draw_number":1238,"draw_date":"2011-10-08","balls":[7,6,6,1]},{"draw_number":1237,"draw_date":"2011-10-07","balls":[3,6,6,3]},{"draw_number":1236,"draw_date":"2011-10-06","balls":[6,3,1,0]},{"draw_number":1235,"draw_date":"2011-10-05","balls":[4,9,1,3]},{"draw_number":1234,"draw_date":"2011-10-04","balls":[4,2,0,7]},{"draw_number":1233,"draw_date":"2011-10-03","balls":[2,5,0,3]},{"draw_number":1232,"draw_date":"2011-10-02","balls":[5,0,8,1]},{"draw_number":1231,"draw_date":"2011-10-01","balls":[5,3,3,5]},{"draw_number":1230,"draw_date":"2011-09-30","balls":[5,7,6,8]},{"draw_number":1229,"draw_date":"2011-09-29","balls":[0,9,8,9]},{"draw_number":1228,"draw_date":"2011-09-28","balls":[9,7,0,0]},{"draw_number":1227,"draw_date":"2011-09-27","balls":[7,0,5,5]},{"draw_number":1226,"draw_date":"2011-09-26","balls":[7,8,0,3]},{"draw_number":1225,"draw_date":"2011-09-25","balls":[7,1,1,3]},{"draw_number":1224,"draw_date":"2011-09-24","balls":[4,4,1,0]},{"draw_number":1223,"draw_date":"2011-09-23","balls":[0,5,6,6]},{"draw_number":1222,"draw_date":"2011-09-22","balls":[8,0,3,4]}]