[{"draw_number":"3046","draw_date":"2016-09-19","balls":["3","8","2","8"]},{"draw_number":"3045","draw_date":"2016-09-18","balls":["3","5","9","3"]},{"draw_number":"3044","draw_date":"2016-09-17","balls":["6","9","5","6"]},{"draw_number":"3043","draw_date":"2016-09-16","balls":["6","6","4","2"]},{"draw_number":"3042","draw_date":"2016-09-15","balls":["8","7","5","1"]},{"draw_number":"3041","draw_date":"2016-09-14","balls":["6","5","7","4"]},{"draw_number":"3040","draw_date":"2016-09-13","balls":["0","8","7","9"]},{"draw_number":"3039","draw_date":"2016-09-12","balls":["3","1","5","8"]},{"draw_number":"3038","draw_date":"2016-09-11","balls":["2","7","2","4"]},{"draw_number":"3037","draw_date":"2016-09-10","balls":["5","8","5","5"]},{"draw_number":"3036","draw_date":"2016-09-09","balls":["0","9","4","4"]},{"draw_number":"3035","draw_date":"2016-09-08","balls":["2","6","4","4"]},{"draw_number":"3034","draw_date":"2016-09-07","balls":["5","4","6","2"]},{"draw_number":"3033","draw_date":"2016-09-06","balls":["3","1","0","2"]},{"draw_number":"3032","draw_date":"2016-09-05","balls":["3","2","9","0"]},{"draw_number":"3031","draw_date":"2016-09-04","balls":["9","0","6","1"]},{"draw_number":"3030","draw_date":"2016-09-03","balls":["0","9","8","3"]},{"draw_number":"3029","draw_date":"2016-09-02","balls":["1","0","5","6"]},{"draw_number":"3028","draw_date":"2016-09-01","balls":["5","8","4","7"]},{"draw_number":"3027","draw_date":"2016-08-31","balls":["8","3","4","5"]},{"draw_number":"3026","draw_date":"2016-08-30","balls":["5","0","2","4"]},{"draw_number":"3025","draw_date":"2016-08-29","balls":["7","0","0","4"]},{"draw_number":"3024","draw_date":"2016-08-28","balls":["8","0","8","8"]},{"draw_number":"3023","draw_date":"2016-08-27","balls":["8","6","4","1"]},{"draw_number":"3022","draw_date":"2016-08-26","balls":["4","4","9","0"]}]