[{"draw_number":"20","draw_date":"1992-05-02","balls":["2","2","4"]},{"draw_number":"19","draw_date":"1992-05-01","balls":["8","5","9"]},{"draw_number":"18","draw_date":"1992-04-30","balls":["8","1","1"]},{"draw_number":"17","draw_date":"1992-04-29","balls":["4","3","0"]},{"draw_number":"16","draw_date":"1992-04-28","balls":["6","2","8"]},{"draw_number":"15","draw_date":"1992-04-27","balls":["2","4","7"]},{"draw_number":"14","draw_date":"1992-04-26","balls":["7","9","8"]},{"draw_number":"13","draw_date":"1992-04-25","balls":["2","5","7"]},{"draw_number":"12","draw_date":"1992-04-24","balls":["9","3","6"]},{"draw_number":"11","draw_date":"1992-04-23","balls":["9","0","0"]},{"draw_number":"10","draw_date":"1992-04-22","balls":["5","7","3"]},{"draw_number":"9","draw_date":"1992-04-21","balls":["9","6","0"]},{"draw_number":"8","draw_date":"1992-04-20","balls":["0","0","8"]},{"draw_number":"7","draw_date":"1992-04-19","balls":["7","6","3"]},{"draw_number":"6","draw_date":"1992-04-18","balls":["7","8","8"]},{"draw_number":"5","draw_date":"1992-04-17","balls":["0","9","1"]},{"draw_number":"4","draw_date":"1992-04-16","balls":["0","6","7"]},{"draw_number":"3","draw_date":"1992-04-15","balls":["0","7","4"]},{"draw_number":"2","draw_date":"1992-04-14","balls":["8","0","9"]},{"draw_number":"1","draw_date":"1992-04-13","balls":["1","9","5"]}]