[{"draw_number":"5346","draw_date":"2004-11-17","balls":["7","2","6"]},{"draw_number":"5345","draw_date":"2004-11-16","balls":["5","1","3"]},{"draw_number":"5344","draw_date":"2004-11-16","balls":["6","6","6"]},{"draw_number":"5343","draw_date":"2004-11-15","balls":["0","0","6"]},{"draw_number":"5342","draw_date":"2004-11-15","balls":["9","2","5"]},{"draw_number":"5341","draw_date":"2004-11-14","balls":["0","1","9"]},{"draw_number":"5340","draw_date":"2004-11-14","balls":["4","1","5"]},{"draw_number":"5339","draw_date":"2004-11-13","balls":["1","3","3"]},{"draw_number":"5338","draw_date":"2004-11-13","balls":["5","6","0"]},{"draw_number":"5337","draw_date":"2004-11-12","balls":["1","9","1"]},{"draw_number":"5336","draw_date":"2004-11-12","balls":["3","0","7"]},{"draw_number":"5335","draw_date":"2004-11-11","balls":["9","7","2"]},{"draw_number":"5334","draw_date":"2004-11-11","balls":["0","6","0"]},{"draw_number":"5333","draw_date":"2004-11-10","balls":["9","6","2"]},{"draw_number":"5332","draw_date":"2004-11-10","balls":["6","8","6"]},{"draw_number":"5331","draw_date":"2004-11-09","balls":["6","5","9"]},{"draw_number":"5330","draw_date":"2004-11-09","balls":["1","5","1"]},{"draw_number":"5329","draw_date":"2004-11-08","balls":["0","2","0"]},{"draw_number":"5328","draw_date":"2004-11-08","balls":["7","9","7"]},{"draw_number":"5327","draw_date":"2004-11-07","balls":["4","3","0"]},{"draw_number":"5326","draw_date":"2004-11-07","balls":["6","6","1"]},{"draw_number":"5325","draw_date":"2004-11-06","balls":["1","9","9"]},{"draw_number":"5324","draw_date":"2004-11-06","balls":["2","0","3"]},{"draw_number":"5323","draw_date":"2004-11-05","balls":["1","2","0"]},{"draw_number":"5322","draw_date":"2004-11-05","balls":["6","5","0"]}]