[{"draw_number":5846,"draw_date":"2005-07-25","balls":[8,5,3]},{"draw_number":5845,"draw_date":"2005-07-24","balls":[8,1,1]},{"draw_number":5844,"draw_date":"2005-07-24","balls":[6,0,6]},{"draw_number":5843,"draw_date":"2005-07-23","balls":[9,0,2]},{"draw_number":5842,"draw_date":"2005-07-23","balls":[9,1,1]},{"draw_number":5841,"draw_date":"2005-07-22","balls":[2,9,3]},{"draw_number":5840,"draw_date":"2005-07-22","balls":[1,3,4]},{"draw_number":5839,"draw_date":"2005-07-21","balls":[5,0,9]},{"draw_number":5838,"draw_date":"2005-07-21","balls":[4,3,9]},{"draw_number":5837,"draw_date":"2005-07-20","balls":[4,1,1]},{"draw_number":5836,"draw_date":"2005-07-20","balls":[1,2,4]},{"draw_number":5835,"draw_date":"2005-07-19","balls":[6,7,0]},{"draw_number":5834,"draw_date":"2005-07-19","balls":[4,9,5]},{"draw_number":5833,"draw_date":"2005-07-18","balls":[8,3,9]},{"draw_number":5832,"draw_date":"2005-07-18","balls":[8,7,7]},{"draw_number":5831,"draw_date":"2005-07-17","balls":[4,7,3]},{"draw_number":5830,"draw_date":"2005-07-17","balls":[7,9,6]},{"draw_number":5829,"draw_date":"2005-07-16","balls":[4,1,1]},{"draw_number":5828,"draw_date":"2005-07-16","balls":[3,8,4]},{"draw_number":5827,"draw_date":"2005-07-15","balls":[0,6,8]},{"draw_number":5826,"draw_date":"2005-07-15","balls":[1,3,4]},{"draw_number":5825,"draw_date":"2005-07-14","balls":[9,0,0]},{"draw_number":5824,"draw_date":"2005-07-14","balls":[0,5,8]},{"draw_number":5823,"draw_date":"2005-07-13","balls":[9,6,9]},{"draw_number":5822,"draw_date":"2005-07-13","balls":[0,4,6]}]