[{"draw_number":8621,"draw_date":"2009-05-12","balls":[0,6,9]},{"draw_number":8620,"draw_date":"2009-05-12","balls":[1,0,0]},{"draw_number":8619,"draw_date":"2009-05-11","balls":[8,6,9]},{"draw_number":8618,"draw_date":"2009-05-11","balls":[0,6,5]},{"draw_number":8617,"draw_date":"2009-05-10","balls":[8,5,4]},{"draw_number":8616,"draw_date":"2009-05-10","balls":[9,0,9]},{"draw_number":8615,"draw_date":"2009-05-09","balls":[8,0,6]},{"draw_number":8614,"draw_date":"2009-05-09","balls":[5,0,0]},{"draw_number":8613,"draw_date":"2009-05-08","balls":[2,4,1]},{"draw_number":8612,"draw_date":"2009-05-08","balls":[3,2,1]},{"draw_number":8611,"draw_date":"2009-05-07","balls":[8,5,9]},{"draw_number":8610,"draw_date":"2009-05-07","balls":[9,9,0]},{"draw_number":8609,"draw_date":"2009-05-06","balls":[2,0,4]},{"draw_number":8608,"draw_date":"2009-05-06","balls":[9,4,5]},{"draw_number":8607,"draw_date":"2009-05-05","balls":[2,0,9]},{"draw_number":8606,"draw_date":"2009-05-05","balls":[1,8,2]},{"draw_number":8605,"draw_date":"2009-05-04","balls":[7,4,9]},{"draw_number":8604,"draw_date":"2009-05-04","balls":[1,9,7]},{"draw_number":8603,"draw_date":"2009-05-03","balls":[8,8,7]},{"draw_number":8602,"draw_date":"2009-05-03","balls":[6,1,1]},{"draw_number":8601,"draw_date":"2009-05-02","balls":[6,1,9]},{"draw_number":8600,"draw_date":"2009-05-02","balls":[4,3,8]},{"draw_number":8599,"draw_date":"2009-05-01","balls":[2,5,3]},{"draw_number":8598,"draw_date":"2009-05-01","balls":[0,7,9]},{"draw_number":8597,"draw_date":"2009-04-30","balls":[9,4,6]}]