[{"draw_number":1020,"draw_date":"1995-01-27","balls":[8,4,4]},{"draw_number":1019,"draw_date":"1995-01-26","balls":[0,6,2]},{"draw_number":1018,"draw_date":"1995-01-25","balls":[0,8,4]},{"draw_number":1017,"draw_date":"1995-01-24","balls":[0,3,2]},{"draw_number":1016,"draw_date":"1995-01-23","balls":[9,2,7]},{"draw_number":1015,"draw_date":"1995-01-22","balls":[3,5,4]},{"draw_number":1014,"draw_date":"1995-01-21","balls":[5,4,4]},{"draw_number":1013,"draw_date":"1995-01-20","balls":[5,4,0]},{"draw_number":1012,"draw_date":"1995-01-19","balls":[6,4,2]},{"draw_number":1011,"draw_date":"1995-01-18","balls":[4,8,0]},{"draw_number":1010,"draw_date":"1995-01-17","balls":[4,3,8]},{"draw_number":1009,"draw_date":"1995-01-16","balls":[9,4,6]},{"draw_number":1008,"draw_date":"1995-01-15","balls":[0,0,2]},{"draw_number":1007,"draw_date":"1995-01-14","balls":[1,2,4]},{"draw_number":1006,"draw_date":"1995-01-13","balls":[7,9,4]},{"draw_number":1005,"draw_date":"1995-01-12","balls":[0,6,5]},{"draw_number":1004,"draw_date":"1995-01-11","balls":[6,9,8]},{"draw_number":1003,"draw_date":"1995-01-10","balls":[5,4,3]},{"draw_number":1002,"draw_date":"1995-01-09","balls":[1,1,2]},{"draw_number":1001,"draw_date":"1995-01-08","balls":[0,6,8]},{"draw_number":1000,"draw_date":"1995-01-07","balls":[5,6,3]},{"draw_number":999,"draw_date":"1995-01-06","balls":[2,4,7]},{"draw_number":998,"draw_date":"1995-01-05","balls":[6,2,6]},{"draw_number":997,"draw_date":"1995-01-04","balls":[9,1,3]},{"draw_number":996,"draw_date":"1995-01-03","balls":[4,8,9]}]