[{"draw_number":"7653","draw_date":"2014-10-20","balls":["35","6","21","12","28"]},{"draw_number":"7652","draw_date":"2014-10-19","balls":["9","18","32","39","37"]},{"draw_number":"7651","draw_date":"2014-10-18","balls":["25","37","2","5","39"]},{"draw_number":"7650","draw_date":"2014-10-17","balls":["18","1","27","8","12"]},{"draw_number":"7649","draw_date":"2014-10-16","balls":["18","27","11","28","22"]},{"draw_number":"7648","draw_date":"2014-10-15","balls":["36","19","1","29","3"]},{"draw_number":"7647","draw_date":"2014-10-14","balls":["20","9","34","21","14"]},{"draw_number":"7646","draw_date":"2014-10-13","balls":["22","29","27","35","9"]},{"draw_number":"7645","draw_date":"2014-10-12","balls":["32","3","13","31","20"]},{"draw_number":"7644","draw_date":"2014-10-11","balls":["17","14","20","33","16"]},{"draw_number":"7643","draw_date":"2014-10-10","balls":["1","34","6","19","2"]},{"draw_number":"7642","draw_date":"2014-10-09","balls":["28","20","3","21","39"]},{"draw_number":"7641","draw_date":"2014-10-08","balls":["2","39","33","18","23"]},{"draw_number":"7640","draw_date":"2014-10-07","balls":["1","35","30","8","34"]},{"draw_number":"7639","draw_date":"2014-10-06","balls":["10","4","9","32","35"]},{"draw_number":"7638","draw_date":"2014-10-05","balls":["4","12","14","23","24"]},{"draw_number":"7637","draw_date":"2014-10-04","balls":["9","39","22","5","32"]},{"draw_number":"7636","draw_date":"2014-10-03","balls":["3","30","39","11","23"]},{"draw_number":"7635","draw_date":"2014-10-02","balls":["32","3","34","15","26"]},{"draw_number":"7634","draw_date":"2014-10-01","balls":["30","37","15","2","35"]},{"draw_number":"7633","draw_date":"2014-09-30","balls":["8","33","39","20","24"]},{"draw_number":"7632","draw_date":"2014-09-29","balls":["18","13","3","38","2"]},{"draw_number":"7631","draw_date":"2014-09-28","balls":["29","22","23","13","25"]},{"draw_number":"7630","draw_date":"2014-09-27","balls":["16","28","11","21","13"]},{"draw_number":"7629","draw_date":"2014-09-26","balls":["30","21","36","22","10"]}]