[{"draw_number":503,"draw_date":"1994-09-05","balls":[12,19,20,26,36]},{"draw_number":502,"draw_date":"1994-09-04","balls":[1,8,10,19,28]},{"draw_number":501,"draw_date":"1994-09-02","balls":[11,14,27,34,36]},{"draw_number":500,"draw_date":"1994-09-01","balls":[2,10,17,18,19]},{"draw_number":499,"draw_date":"1994-08-30","balls":[6,10,16,30,38]},{"draw_number":498,"draw_date":"1994-08-29","balls":[2,10,11,23,33]},{"draw_number":497,"draw_date":"1994-08-28","balls":[4,5,9,15,25]},{"draw_number":496,"draw_date":"1994-08-26","balls":[21,26,36,38,39]},{"draw_number":495,"draw_date":"1994-08-25","balls":[17,22,28,31,38]},{"draw_number":494,"draw_date":"1994-08-23","balls":[5,15,22,38,39]},{"draw_number":493,"draw_date":"1994-08-22","balls":[11,12,20,23,38]},{"draw_number":492,"draw_date":"1994-08-21","balls":[8,18,24,30,31]},{"draw_number":491,"draw_date":"1994-08-19","balls":[7,13,14,30,31]},{"draw_number":490,"draw_date":"1994-08-18","balls":[1,2,20,36,39]},{"draw_number":489,"draw_date":"1994-08-16","balls":[23,29,30,32,35]},{"draw_number":488,"draw_date":"1994-08-15","balls":[9,12,15,31,32]},{"draw_number":487,"draw_date":"1994-08-14","balls":[9,25,26,34,39]},{"draw_number":486,"draw_date":"1994-08-12","balls":[9,13,16,23,33]},{"draw_number":485,"draw_date":"1994-08-11","balls":[11,13,22,25,27]},{"draw_number":484,"draw_date":"1994-08-09","balls":[16,24,27,28,36]},{"draw_number":483,"draw_date":"1994-08-08","balls":[6,8,17,18,21]},{"draw_number":482,"draw_date":"1994-08-07","balls":[8,11,21,32,35]},{"draw_number":481,"draw_date":"1994-08-05","balls":[11,23,24,28,29]},{"draw_number":480,"draw_date":"1994-08-04","balls":[1,17,21,22,26]},{"draw_number":479,"draw_date":"1994-08-02","balls":[9,18,23,26,38]}]