[{"draw_number":6378,"draw_date":"2011-04-24","balls":[38,15,9,39,3]},{"draw_number":6377,"draw_date":"2011-04-23","balls":[10,9,7,15,20]},{"draw_number":6376,"draw_date":"2011-04-22","balls":[7,31,19,10,13]},{"draw_number":6375,"draw_date":"2011-04-21","balls":[6,31,2,19,27]},{"draw_number":6374,"draw_date":"2011-04-20","balls":[37,9,10,39,38]},{"draw_number":6373,"draw_date":"2011-04-19","balls":[6,5,36,39,28]},{"draw_number":6372,"draw_date":"2011-04-18","balls":[14,13,28,7,3]},{"draw_number":6371,"draw_date":"2011-04-17","balls":[34,37,6,38,9]},{"draw_number":6370,"draw_date":"2011-04-16","balls":[30,21,10,26,29]},{"draw_number":6369,"draw_date":"2011-04-15","balls":[8,32,16,19,1]},{"draw_number":6368,"draw_date":"2011-04-14","balls":[28,25,39,37,17]},{"draw_number":6367,"draw_date":"2011-04-13","balls":[31,26,19,7,20]},{"draw_number":6366,"draw_date":"2011-04-12","balls":[11,22,10,13,38]},{"draw_number":6365,"draw_date":"2011-04-11","balls":[16,36,6,28,13]},{"draw_number":6364,"draw_date":"2011-04-10","balls":[17,37,30,20,28]},{"draw_number":6363,"draw_date":"2011-04-09","balls":[28,34,19,26,15]},{"draw_number":6362,"draw_date":"2011-04-08","balls":[7,39,17,24,10]},{"draw_number":6361,"draw_date":"2011-04-07","balls":[3,37,22,30,34]},{"draw_number":6360,"draw_date":"2011-04-06","balls":[31,21,39,27,3]},{"draw_number":6359,"draw_date":"2011-04-05","balls":[8,35,5,24,6]},{"draw_number":6358,"draw_date":"2011-04-04","balls":[10,36,26,35,1]},{"draw_number":6357,"draw_date":"2011-04-03","balls":[10,29,34,37,28]},{"draw_number":6356,"draw_date":"2011-04-02","balls":[5,39,4,20,27]},{"draw_number":6355,"draw_date":"2011-04-01","balls":[22,24,29,28,5]},{"draw_number":6354,"draw_date":"2011-03-31","balls":[22,34,29,20,19]}]