[{"draw_number":9178,"draw_date":"2018-12-23","balls":[18,5,34,23,2]},{"draw_number":9177,"draw_date":"2018-12-22","balls":[35,23,28,27,6]},{"draw_number":9176,"draw_date":"2018-12-21","balls":[12,32,31,5,10]},{"draw_number":9175,"draw_date":"2018-12-20","balls":[15,31,11,4,2]},{"draw_number":9174,"draw_date":"2018-12-19","balls":[5,6,7,25,3]},{"draw_number":9173,"draw_date":"2018-12-18","balls":[1,28,32,18,4]},{"draw_number":9172,"draw_date":"2018-12-17","balls":[39,31,18,24,26]},{"draw_number":9171,"draw_date":"2018-12-16","balls":[20,38,31,35,2]},{"draw_number":9170,"draw_date":"2018-12-15","balls":[17,8,34,18,13]},{"draw_number":9169,"draw_date":"2018-12-14","balls":[1,18,22,36,35]},{"draw_number":9168,"draw_date":"2018-12-13","balls":[25,27,32,20,1]},{"draw_number":9167,"draw_date":"2018-12-12","balls":[17,8,4,1,28]},{"draw_number":9166,"draw_date":"2018-12-11","balls":[20,16,25,35,1]},{"draw_number":9165,"draw_date":"2018-12-10","balls":[12,17,1,34,14]},{"draw_number":9164,"draw_date":"2018-12-09","balls":[9,28,5,19,14]},{"draw_number":9163,"draw_date":"2018-12-08","balls":[11,4,13,25,21]},{"draw_number":9162,"draw_date":"2018-12-07","balls":[28,30,33,34,26]},{"draw_number":9161,"draw_date":"2018-12-06","balls":[11,38,1,36,2]},{"draw_number":9160,"draw_date":"2018-12-05","balls":[20,36,18,37,25]},{"draw_number":9159,"draw_date":"2018-12-04","balls":[34,4,9,5,29]},{"draw_number":9158,"draw_date":"2018-12-03","balls":[16,2,24,27,38]},{"draw_number":9157,"draw_date":"2018-12-02","balls":[39,31,29,23,38]},{"draw_number":9156,"draw_date":"2018-12-01","balls":[19,21,32,4,1]},{"draw_number":9155,"draw_date":"2018-11-30","balls":[21,26,6,23,13]},{"draw_number":9154,"draw_date":"2018-11-29","balls":[22,30,10,31,13]}]