[{"draw_number":"3903","draw_date":"2004-07-14","balls":["4","10","12","18","26"]},{"draw_number":"3902","draw_date":"2004-07-13","balls":["24","29","33","35","37"]},{"draw_number":"3901","draw_date":"2004-07-12","balls":["2","6","7","15","37"]},{"draw_number":"3900","draw_date":"2004-07-11","balls":["3","6","15","21","22"]},{"draw_number":"3899","draw_date":"2004-07-10","balls":["7","23","26","28","31"]},{"draw_number":"3898","draw_date":"2004-07-09","balls":["2","5","8","21","38"]},{"draw_number":"3897","draw_date":"2004-07-08","balls":["17","23","27","32","33"]},{"draw_number":"3896","draw_date":"2004-07-07","balls":["9","11","14","16","39"]},{"draw_number":"3895","draw_date":"2004-07-06","balls":["8","9","10","13","34"]},{"draw_number":"3894","draw_date":"2004-07-05","balls":["6","9","16","24","34"]},{"draw_number":"3893","draw_date":"2004-07-04","balls":["2","5","4","34","39"]},{"draw_number":"3892","draw_date":"2004-07-03","balls":["4","10","16","26","39"]},{"draw_number":"3891","draw_date":"2004-07-02","balls":["6","11","15","23","35"]},{"draw_number":"3890","draw_date":"2004-07-01","balls":["5","18","22","24","34"]},{"draw_number":"3889","draw_date":"2004-06-30","balls":["17","25","34","35","38"]},{"draw_number":"3888","draw_date":"2004-06-29","balls":["2","19","27","32","37"]},{"draw_number":"3887","draw_date":"2004-06-28","balls":["8","11","19","27","37"]},{"draw_number":"3886","draw_date":"2004-06-27","balls":["8","9","13","18","28"]},{"draw_number":"3885","draw_date":"2004-06-26","balls":["1","2","12","13","30"]},{"draw_number":"3884","draw_date":"2004-06-25","balls":["11","20","21","23","28"]},{"draw_number":"3883","draw_date":"2004-06-24","balls":["5","8","11","16","39"]},{"draw_number":"3882","draw_date":"2004-06-23","balls":["10","14","33","35","39"]},{"draw_number":"3881","draw_date":"2004-06-22","balls":["1","5","6","8","23"]},{"draw_number":"3880","draw_date":"2004-06-21","balls":["1","3","4","7","27"]},{"draw_number":"3879","draw_date":"2004-06-20","balls":["1","5","12","26","32"]}]