[{"draw_number":484,"draw_date":"2010-02-09","balls":[48,17,26,2,20,12],"megaball":12},{"draw_number":483,"draw_date":"2010-02-05","balls":[10,53,20,51,45,41],"megaball":41},{"draw_number":482,"draw_date":"2010-02-02","balls":[6,49,7,27,26,9],"megaball":9},{"draw_number":481,"draw_date":"2010-01-29","balls":[23,1,38,22,10,19],"megaball":19},{"draw_number":480,"draw_date":"2010-01-26","balls":[38,7,39,8,48,22],"megaball":22},{"draw_number":479,"draw_date":"2010-01-22","balls":[27,52,13,8,28,9],"megaball":9},{"draw_number":478,"draw_date":"2010-01-19","balls":[34,41,4,5,38,18],"megaball":18},{"draw_number":477,"draw_date":"2010-01-15","balls":[7,19,4,38,21,29],"megaball":29},{"draw_number":476,"draw_date":"2010-01-12","balls":[31,56,9,5,37,16],"megaball":16},{"draw_number":475,"draw_date":"2010-01-08","balls":[36,18,31,43,20,33],"megaball":33},{"draw_number":474,"draw_date":"2010-01-05","balls":[28,50,13,39,55,10],"megaball":10},{"draw_number":473,"draw_date":"2010-01-01","balls":[27,6,41,8,40,21],"megaball":21},{"draw_number":472,"draw_date":"2009-12-29","balls":[2,35,5,29,51,3],"megaball":3},{"draw_number":471,"draw_date":"2009-12-25","balls":[52,4,44,16,54,20],"megaball":20},{"draw_number":470,"draw_date":"2009-12-22","balls":[39,35,45,3,33,13],"megaball":13},{"draw_number":469,"draw_date":"2009-12-18","balls":[44,49,30,20,10,24],"megaball":24},{"draw_number":468,"draw_date":"2009-12-15","balls":[32,27,31,36,47,35],"megaball":35},{"draw_number":467,"draw_date":"2009-12-11","balls":[34,21,27,2,44,45],"megaball":45},{"draw_number":466,"draw_date":"2009-12-08","balls":[28,30,20,46,23,29],"megaball":29},{"draw_number":465,"draw_date":"2009-12-04","balls":[51,41,33,4,56,38],"megaball":38},{"draw_number":464,"draw_date":"2009-12-01","balls":[53,17,52,39,30,21],"megaball":21},{"draw_number":463,"draw_date":"2009-11-27","balls":[12,25,39,45,37,11],"megaball":11},{"draw_number":462,"draw_date":"2009-11-24","balls":[37,35,50,10,11,12],"megaball":12},{"draw_number":461,"draw_date":"2009-11-20","balls":[3,4,56,7,16,39],"megaball":39},{"draw_number":460,"draw_date":"2009-11-17","balls":[22,50,8,49,27,28],"megaball":28}]